[
    {
        "code": "makebalancerune-quartz",
        "enabled": true,
        "attributes": {
            "catalyst": "runestory:rune-blank",
            "reagents": {
                "game:clearquartz": 1
            },
            "outputs": {
                "runestory:rune-balance": 2
            }
        }
    },
    {
        "code": "makebalancerune-glass",
        "enabled": true,
        "attributes": {
            "catalyst": "runestory:rune-blank",
            "reagents": {
                "game:glass-plain": 1
            },
            "outputs": {
                "runestory:rune-balance": 4
            }
        }
    },
    {
        "code": "makebalancerune-crushed",
        "enabled": true,
        "attributes": {
            "catalyst": "runestory:rune-blank",
            "reagents": {
                "game:crushed-quartz": 1
            },
            "outputs": {
                "runestory:rune-balance": 2
            }
        }
    },
    {
        "code": "makebalancerune-beeswax",
        "enabled": true,
        "attributes": {
            "catalyst": "runestory:rune-blank",
            "reagents": {
                "game:beeswax": 1
            },
            "outputs": {
                "runestory:rune-balance": 8
            }
        }
    }
]