{
    "code": "burnerator",
    "shape": { "base": "block/machines/burnerator" },
    "creativeinventory": {
        "general": [ "*" ],
        "lensstorytab": [ "*" ]
    },
    "class": "lensfurnacegenblock",
    "entityClass": "lensfurnacegen",
    "entityBehaviors": [
        { "name": "lensfurnacegenbehavior" },
        { "name": "Mana" }
    ],
    "attributes": {
        "handbook": {
            "extraSections": [
                {
                    "title": "handbook-block-burnerator-title",
                    "text": "handbook-block-burnerator-text"
                }
            ],
            "include": true
        }
    },
    "blockmaterial": "Metal",
    "replaceable": 900,
    "lightAbsorption": 99,
    "maxStackSize": 32,
    "materialDensity": 700,
    "resistance": 4,
    "sideopaque": {
        "all": false,
        "down":true

    },
    "sidesolid": {
        "all": true,
        "up": false
    }
}
